{
    "slug": "boxing/gloves/how-to-break-in-boxing-gloves",
    "label": "How to Break In Boxing Gloves",
    "title": "How to Break In Boxing Gloves Safely",
    "subtitle": "A practical beginner guide to softening new boxing gloves without damaging the padding, leather, or wrist support.",
    "description": "Learn how to break in boxing gloves safely, how long it takes, what mistakes to avoid, and when tight gloves are actually the wrong fit.",
    "canonical": "https://sportloom.com/boxing/gloves/how-to-break-in-boxing-gloves",
    "coverImage": "/images/articles/how-to-break-in-boxing-gloves/Hero.webp",
    "altText": "New boxing gloves on the table.",
    "date": "2026-07-09",
    "readingTime": "13 min",
    "contentType": "article",
    "articleType": "informational",
    "category": "boxing-gloves",
    "featured": false,
    "published": true,
    "tags": [
        "boxing",
        "gloves",
        "care",
        "gear",
        "beginner",
        "heavy bag",
        "sparring",
        "hand protection"
    ],
    "relatedSlugs": [
        {
            "href": "/boxing/gloves/how-tight-should-boxing-gloves-fit",
            "label": "How Tight Should Boxing Gloves Fit?"
        },
        {
            "href": "/boxing/gloves/boxing-gloves-size-guide",
            "label": "Boxing Gloves Size Guide"
        },
        {
            "href": "/boxing/gloves/boxing-glove-size-calculator",
            "label": "Boxing Glove Size Calculator"
        },
        {
            "href": "/articles/how-to-clean-boxing-gloves",
            "label": "How to Clean Boxing Gloves"
        },
        {
            "href": "/articles/how-to-wrap-your-hands-for-boxing",
            "label": "How to Wrap Your Hands for Boxing"
        },
        {
            "href": "/boxing/gloves/best-boxing-gloves-for-wrist-support",
            "label": "Best Boxing Gloves for Wrist Support"
        },
        {
            "href": "/boxing/gloves/best-boxing-gloves-for-heavy-bag",
            "label": "Best Boxing Gloves for Heavy Bag"
        }
    ]
}
